vid2text/__init__.py
vid2text/__main__.py
vid2text/cli.py
vid2text/config.py
vid2text/database.py
vid2text/processors.py
vid2text/transcription.py
vid2text-0.1.0.dist-info/METADATA
vid2text-0.1.0.dist-info/WHEEL
vid2text-0.1.0.dist-info/entry_points.txt
vid2text-0.1.0.dist-info/top_level.txt
vid2text-0.1.0.dist-info/RECORD
